helenium/__init__.py
helenium/base.py
helenium/selenium_loader.py
helenium-0.1.5.dist-info/LICENSE
helenium-0.1.5.dist-info/METADATA
helenium-0.1.5.dist-info/WHEEL
helenium-0.1.5.dist-info/top_level.txt
helenium-0.1.5.dist-info/RECORD
