Metadata-Version: 2.1
Name: helenium
Version: 0.1.5
Summary: Simple Selenium Load Helper Package
License: MIT License        
Project-URL: Homepage, https://github.com/Indosaram/helenium.git
Requires-Python: >=3.8
License-File: LICENSE
Requires-Dist: selenium (>=4.3.0)
Requires-Dist: requests (>=2.28.0)
